testing_capnpy-0.0.4.dist-info/top_level.txt
testing_capnpy-0.0.4.dist-info/RECORD
testing_capnpy-0.0.4.dist-info/METADATA
testing_capnpy-0.0.4.dist-info/LICENSE
testing_capnpy-0.0.4.dist-info/entry_points.txt
testing_capnpy-0.0.4.dist-info/WHEEL
capnpy/ptr.so
capnpy/util.py
capnpy/_hash.py
capnpy/ptr.py
capnpy/schema.py
capnpy/struct_.py
capnpy/anypointer.py
capnpy/convert_case.py
capnpy/annotate.py
capnpy/_hash_cpython.c
capnpy/filelike.py
capnpy/blob.py
capnpy/enum.py
capnpy/__main__.py
capnpy/buffered.py
capnpy/printer.py
capnpy/type.py
capnpy/list.py
capnpy/schema_extended.py
capnpy/annotate_extended.py
capnpy/message.py
capnpy/packing.py
capnpy/ptr.pyx
capnpy/__init__.py
capnpy/reflection.py
capnpy/compiler/util.py
capnpy/compiler/struct_.py
capnpy/compiler/misc.py
capnpy/compiler/compiler.py
capnpy/compiler/field.py
capnpy/compiler/module.py
capnpy/compiler/enum.py
capnpy/compiler/structor.py
capnpy/compiler/node.py
capnpy/compiler/distutils.py
capnpy/compiler/fieldtree.py
capnpy/compiler/__init__.py
capnpy/compiler/request.py
capnpy/ext/__init__.py
capnpy/floatrepr/__init__.py
capnpy/floatrepr/build.py
capnpy/segment/segment.py
capnpy/segment/_copy_list.py
capnpy/segment/_copy_pointer.py
capnpy/segment/builder.py
capnpy/segment/endof.py
capnpy/segment/base.py
capnpy/segment/__init__.py
capnpy/benchmarks/test_message.py
capnpy/benchmarks/test_ctor.py
capnpy/benchmarks/test_unpack.py
capnpy/benchmarks/test_buffered.py
capnpy/benchmarks/__init__.py
capnpy/benchmarks/test_benchmarks.py
capnpy/benchmarks/support.py
capnpy/testing/test_message.py
capnpy/testing/test__hash.py
capnpy/testing/test_blob.py
capnpy/testing/test_ptr.py
capnpy/testing/test_enum.py
capnpy/testing/test_annotate.py
capnpy/testing/test_filelike.py
capnpy/testing/test_util.py
capnpy/testing/test_buffered.py
capnpy/testing/test_packing.py
capnpy/testing/test_list.py
capnpy/testing/test_main.py
capnpy/testing/__init__.py
capnpy/testing/test_floatrepr.py
capnpy/testing/test_convert_case.py
capnpy/testing/test_struct_.py
capnpy/testing/compiler/test_fieldtree.py
capnpy/testing/compiler/test_field.py
capnpy/testing/compiler/test_standalone.py
