Metadata-Version: 2.1
Name: testing-capnpy
Version: 0.0.4
Summary: UNKNOWN
Home-page: https://github.com/antocuni/capnpy
Author: Antonio Cuni
Author-email: anto.cuni@gmail.com
License: UNKNOWN
Platform: UNKNOWN
Requires-Dist: pypytools (>=0.3.3)
Requires-Dist: docopt
Requires-Dist: six
Requires-Dist: cython (>=0.25)
